ml2service/__init__.py
ml2service/cli.py
ml2service/models/__init__.py
ml2service/models/base.py
ml2service/models/loader.py
ml2service/serializers/__init__.py
ml2service/serializers/base.py
ml2service/services/__init__.py
ml2service/services/base.py
ml2service/services/dynamic.py
ml2service/services/runners/__init__.py
ml2service/services/runners/base.py
ml2service/services/runners/fastapi/__init__.py
ml2service/services/runners/fastapi/factory.py
ml2service/services/runners/fastapi/runner.py
ml2service/services/static.py
ml2service/storages/__init__.py
ml2service/storages/base.py
ml2service/storages/in_memory.py
ml2service/storages/memoize.py
ml2service/storages/serialized.py
ml2service/strict_typing.py
ml2service-0.1.0.dist-info/entry_points.txt
ml2service-0.1.0.dist-info/LICENSE
ml2service-0.1.0.dist-info/WHEEL
ml2service-0.1.0.dist-info/METADATA
ml2service-0.1.0.dist-info/RECORD
