Metadata-Version: 2.1
Name: ml2service
Version: 0.1.0
Summary: 
Author: zerlok
Author-email: denergytro@gmail.com
Requires-Python: >=3.9,<4.0
Classifier: Programming Language :: Python :: 3
Classifier: Programming Language :: Python :: 3.9
Classifier: Programming Language :: Python :: 3.10
Provides-Extra: fastapi-uvicorn
Requires-Dist: click (>=8.1.3,<9.0.0)
Requires-Dist: fastapi (>=0.79.0,<0.80.0); extra == "fastapi-uvicorn"
Requires-Dist: pydantic (>=1.9.1,<2.0.0)
Requires-Dist: uvicorn[standard] (>=0.18.2,<0.19.0); extra == "fastapi-uvicorn"
